vvv_docker/__init__.py
vvv_docker/_cdp.py
vvv_docker/scripts/flask_api.py
vvv_docker/scripts/onnxruntime_1.py
vvv_docker/websocket/__init__.py
vvv_docker/websocket/_abnf.py
vvv_docker/websocket/_app.py
vvv_docker/websocket/_cookiejar.py
vvv_docker/websocket/_core.py
vvv_docker/websocket/_exceptions.py
vvv_docker/websocket/_handshake.py
vvv_docker/websocket/_http.py
vvv_docker/websocket/_logging.py
vvv_docker/websocket/_socket.py
vvv_docker/websocket/_ssl_compat.py
vvv_docker/websocket/_url.py
vvv_docker/websocket/_utils.py
vvv_docker/websocket/_wsdump.py
vvv_docker/websocket/py.typed
vvv_docker-0.2.8.dist-info/METADATA
vvv_docker-0.2.8.dist-info/WHEEL
vvv_docker-0.2.8.dist-info/entry_points.txt
vvv_docker-0.2.8.dist-info/top_level.txt
vvv_docker-0.2.8.dist-info/RECORD
