Metadata-Version: 2.1
Name: vvv_docker
Version: 0.2.8
Requires-Dist: paramiko
